morgoth/__init__.py
morgoth/__main__.py
morgoth/conformal_prediction.py
morgoth/morgoth.py
morgoth/multi_rf_main.py
morgoth/multivariate_dt.py
morgoth/similarity_test_train.py
morgoth-1.5.dist-info/METADATA
morgoth-1.5.dist-info/WHEEL
morgoth-1.5.dist-info/top_level.txt
morgoth-1.5.dist-info/RECORD
