Metadata-Version: 2.1
Name: morgoth
Version: 1.5
Summary: Interpretable and reliable multivariate random forest for simultaneous classification and regression
Home-page: https://github.com/volkamerlab/MORGOTH.git
Author: Lisa-Marie Rolli
Author-email: lisa-marie.rolli@uni-saarland.de
Classifier: Programming Language :: Python :: 3
Classifier: License :: OSI Approved :: MIT License
Requires-Dist: pandas
Requires-Dist: numpy
Requires-Dist: scipy
Requires-Dist: scikit-learn
Requires-Dist: multiprocess
Requires-Dist: fireducks; sys_platform == "linux"
